vecto/__init__.py
vecto/client.py
vecto/exceptions.py
vecto/schema.py
vecto/vecto_requests.py
vecto/vector_space.py
vecto_sdk-0.2.3.dist-info/LICENSE
vecto_sdk-0.2.3.dist-info/METADATA
vecto_sdk-0.2.3.dist-info/WHEEL
vecto_sdk-0.2.3.dist-info/top_level.txt
vecto_sdk-0.2.3.dist-info/RECORD
