Metadata-Version: 2.1
Name: vecto-sdk
Version: 0.2.3
Summary: Official Python SDK for Vecto
Home-page: https://github.com/XpressAI/vecto-python-sdk
Author: Xpress AI
Author-email: eduardo@xpress.ai
License: UNKNOWN
Project-URL: Documentation, https://docs.vecto.ai/
Project-URL: Source, https://github.com/XpressAI/vecto-python-sdk
Project-URL: Issues, https://github.com/XpressAI/vecto-python-sdk/issues
Keywords: vector-database,vector-search
Platform: UNKNOWN
Classifier: Programming Language :: Python :: 3
Classifier: License :: OSI Approved :: Apache Software License
Classifier: Operating System :: OS Independent
Requires-Python: >=3.8
License-File: LICENSE
Requires-Dist: requests
Requires-Dist: requests-toolbelt
